{"LOCATION":[
{"Project1":[{"Name":"maxServerMeta","Value":128},{"Name":"maxTotalInstances","Value":10},{"Name":"maxPersonality","Value":5},{"Name":"totalServerGroupsUsed","Value":0},{"Name":"maxImageMeta","Value":128},{"Name":"maxPersonalitySize","Value":10240},{"Name":"maxTotalRAMSize","Value":51200},{"Name":"maxServerGroups","Value":10},{"Name":"maxSecurityGroupRules","Value":20},{"Name":"maxTotalKeypairs","Value":100},{"Name":"totalCoresUsed","Value":4},{"Name":"totalRAMUsed","Value":8192},{"Name":"maxSecurityGroups","Value":10},{"Name":"totalFloatingIpsUsed","Value":0},{"Name":"totalInstancesUsed","Value":1},{"Name":"maxServerGroupMembers","Value":10},{"Name":"maxTotalFloatingIps","Value":10},{"Name":"totalSecurityGroupsUsed","Value":1},{"Name":"maxTotalCores","Value":20},{"Name":"totalSnapshotsUsed","Value":0},{"Name":"maxTotalBackups","Value":10},{"Name":"maxTotalVolumeGigabytes","Value":1000},{"Name":"maxTotalSnapshots","Value":10},{"Name":"maxTotalBackupGigabytes","Value":1000},{"Name":"totalBackupGigabytesUsed","Value":0},{"Name":"maxTotalVolumes","Value":10},{"Name":"totalVolumesUsed","Value":1},{"Name":"totalBackupsUsed","Value":0},{"Name":"totalGigabytesUsed","Value":2}]},
{"Project2":[{"Name":"maxServerMeta","Value":128},{"Name":"maxTotalInstances","Value":10},{"Name":"maxPersonality","Value":5},{"Name":"totalServerGroupsUsed","Value":0},{"Name":"maxImageMeta","Value":128},{"Name":"maxPersonalitySize","Value":10240},{"Name":"maxTotalRAMSize","Value":417792},{"Name":"maxServerGroups","Value":10},{"Name":"maxSecurityGroupRules","Value":20},{"Name":"maxTotalKeypairs","Value":100},{"Name":"totalCoresUsed","Value":0},{"Name":"totalRAMUsed","Value":0},{"Name":"maxSecurityGroups","Value":10},{"Name":"totalFloatingIpsUsed","Value":0},{"Name":"totalInstancesUsed","Value":0},{"Name":"maxServerGroupMembers","Value":10},{"Name":"maxTotalFloatingIps","Value":10},{"Name":"totalSecurityGroupsUsed","Value":0},{"Name":"maxTotalCores","Value":84},{"Name":"totalSnapshotsUsed","Value":0},{"Name":"maxTotalBackups","Value":10},{"Name":"maxTotalVolumeGigabytes","Value":1000},{"Name":"maxTotalSnapshots","Value":10},{"Name":"maxTotalBackupGigabytes","Value":1000},{"Name":"totalBackupGigabytesUsed","Value":0},{"Name":"maxTotalVolumes","Value":10},{"Name":"totalVolumesUsed","Value":1},{"Name":"totalBackupsUsed","Value":0},{"Name":"totalGigabytesUsed","Value":2}]},
{"Project3":[{"Name":"maxServerMeta","Value":128},{"Name":"maxTotalInstances","Value":10},{"Name":"maxPersonality","Value":5},{"Name":"totalServerGroupsUsed","Value":0},{"Name":"maxImageMeta","Value":128},{"Name":"maxPersonalitySize","Value":10240},{"Name":"maxTotalRAMSize","Value":51200},{"Name":"maxServerGroups","Value":10},{"Name":"maxSecurityGroupRules","Value":20},{"Name":"maxTotalKeypairs","Value":100},{"Name":"totalCoresUsed","Value":0},{"Name":"totalRAMUsed","Value":0},{"Name":"maxSecurityGroups","Value":10},{"Name":"totalFloatingIpsUsed","Value":0},{"Name":"totalInstancesUsed","Value":0},{"Name":"maxServerGroupMembers","Value":10},{"Name":"maxTotalFloatingIps","Value":10},{"Name":"totalSecurityGroupsUsed","Value":0},{"Name":"maxTotalCores","Value":20},{"Name":"totalSnapshotsUsed","Value":0},{"Name":"maxTotalBackups","Value":10},{"Name":"maxTotalVolumeGigabytes","Value":1000},{"Name":"maxTotalSnapshots","Value":10},{"Name":"maxTotalBackupGigabytes","Value":1000},{"Name":"totalBackupGigabytesUsed","Value":0},{"Name":"maxTotalVolumes","Value":10},{"Name":"totalVolumesUsed","Value":1},{"Name":"totalBackupsUsed","Value":0},{"Name":"totalGigabytesUsed","Value":2}]},
{"Project4":[{"Name":"maxServerMeta","Value":128},{"Name":"maxTotalInstances","Value":10},{"Name":"maxPersonality","Value":5},{"Name":"totalServerGroupsUsed","Value":0},{"Name":"maxImageMeta","Value":128},{"Name":"maxPersonalitySize","Value":10240},{"Name":"maxTotalRAMSize","Value":51200},{"Name":"maxServerGroups","Value":10},{"Name":"maxSecurityGroupRules","Value":20},{"Name":"maxTotalKeypairs","Value":100},{"Name":"totalCoresUsed","Value":8},{"Name":"totalRAMUsed","Value":16384},{"Name":"maxSecurityGroups","Value":10},{"Name":"totalFloatingIpsUsed","Value":0},{"Name":"totalInstancesUsed","Value":1},{"Name":"maxServerGroupMembers","Value":10},{"Name":"maxTotalFloatingIps","Value":10},{"Name":"totalSecurityGroupsUsed","Value":1},{"Name":"maxTotalCores","Value":20},{"Name":"totalSnapshotsUsed","Value":0},{"Name":"maxTotalBackups","Value":10},{"Name":"maxTotalVolumeGigabytes","Value":1000},{"Name":"maxTotalSnapshots","Value":10},{"Name":"maxTotalBackupGigabytes","Value":1000},{"Name":"totalBackupGigabytesUsed","Value":0},{"Name":"maxTotalVolumes","Value":10},{"Name":"totalVolumesUsed","Value":1},{"Name":"totalBackupsUsed","Value":0},{"Name":"totalGigabytesUsed","Value":2}]},
{"Project5":[{"Name":"maxServerMeta","Value":128},{"Name":"maxTotalInstances","Value":25},{"Name":"maxPersonality","Value":5},{"Name":"totalServerGroupsUsed","Value":0},{"Name":"maxImageMeta","Value":128},{"Name":"maxPersonalitySize","Value":10240},{"Name":"maxTotalRAMSize","Value":61440},{"Name":"maxServerGroups","Value":10},{"Name":"maxSecurityGroupRules","Value":20},{"Name":"maxTotalKeypairs","Value":100},{"Name":"totalCoresUsed","Value":16},{"Name":"totalRAMUsed","Value":32768},{"Name":"maxSecurityGroups","Value":10},{"Name":"totalFloatingIpsUsed","Value":0},{"Name":"totalInstancesUsed","Value":2},{"Name":"maxServerGroupMembers","Value":10},{"Name":"maxTotalFloatingIps","Value":10},{"Name":"totalSecurityGroupsUsed","Value":1},{"Name":"maxTotalCores","Value":36},{"Name":"totalSnapshotsUsed","Value":0},{"Name":"maxTotalBackups","Value":10},{"Name":"maxTotalVolumeGigabytes","Value":1000},{"Name":"maxTotalSnapshots","Value":10},{"Name":"maxTotalBackupGigabytes","Value":1000},{"Name":"totalBackupGigabytesUsed","Value":0},{"Name":"maxTotalVolumes","Value":10},{"Name":"totalVolumesUsed","Value":1},{"Name":"totalBackupsUsed","Value":0},{"Name":"totalGigabytesUsed","Value":2}]},
{"Project6":[{"Name":"maxServerMeta","Value":128},{"Name":"maxTotalInstances","Value":10},{"Name":"maxPersonality","Value":5},{"Name":"totalServerGroupsUsed","Value":0},{"Name":"maxImageMeta","Value":128},{"Name":"maxPersonalitySize","Value":10240},{"Name":"maxTotalRAMSize","Value":51200},{"Name":"maxServerGroups","Value":10},{"Name":"maxSecurityGroupRules","Value":20},{"Name":"maxTotalKeypairs","Value":100},{"Name":"totalCoresUsed","Value":0},{"Name":"totalRAMUsed","Value":0},{"Name":"maxSecurityGroups","Value":10},{"Name":"totalFloatingIpsUsed","Value":0},{"Name":"totalInstancesUsed","Value":0},{"Name":"maxServerGroupMembers","Value":10},{"Name":"maxTotalFloatingIps","Value":10},{"Name":"totalSecurityGroupsUsed","Value":0},{"Name":"maxTotalCores","Value":20},{"Name":"totalSnapshotsUsed","Value":0},{"Name":"maxTotalBackups","Value":10},{"Name":"maxTotalVolumeGigabytes","Value":1000},{"Name":"maxTotalSnapshots","Value":10},{"Name":"maxTotalBackupGigabytes","Value":1000},{"Name":"totalBackupGigabytesUsed","Value":0},{"Name":"maxTotalVolumes","Value":10},{"Name":"totalVolumesUsed","Value":1},{"Name":"totalBackupsUsed","Value":0},{"Name":"totalGigabytesUsed","Value":2}]},
{"Project7":[{"Name":"maxServerMeta","Value":128},{"Name":"maxTotalInstances","Value":10},{"Name":"maxPersonality","Value":5},{"Name":"totalServerGroupsUsed","Value":0},{"Name":"maxImageMeta","Value":128},{"Name":"maxPersonalitySize","Value":10240},{"Name":"maxTotalRAMSize","Value":51200},{"Name":"maxServerGroups","Value":10},{"Name":"maxSecurityGroupRules","Value":20},{"Name":"maxTotalKeypairs","Value":100},{"Name":"totalCoresUsed","Value":10},{"Name":"totalRAMUsed","Value":20480},{"Name":"maxSecurityGroups","Value":10},{"Name":"totalFloatingIpsUsed","Value":0},{"Name":"totalInstancesUsed","Value":2},{"Name":"maxServerGroupMembers","Value":10},{"Name":"maxTotalFloatingIps","Value":10},{"Name":"totalSecurityGroupsUsed","Value":1},{"Name":"maxTotalCores","Value":20},{"Name":"totalSnapshotsUsed","Value":0},{"Name":"maxTotalBackups","Value":10},{"Name":"maxTotalVolumeGigabytes","Value":1000},{"Name":"maxTotalSnapshots","Value":10},{"Name":"maxTotalBackupGigabytes","Value":1000},{"Name":"totalBackupGigabytesUsed","Value":0},{"Name":"maxTotalVolumes","Value":10},{"Name":"totalVolumesUsed","Value":1},{"Name":"totalBackupsUsed","Value":0},{"Name":"totalGigabytesUsed","Value":2}]},
{"admin":[{"Name":"maxServerMeta","Value":128},{"Name":"maxTotalInstances","Value":10},{"Name":"maxPersonality","Value":5},{"Name":"totalServerGroupsUsed","Value":0},{"Name":"maxImageMeta","Value":128},{"Name":"maxPersonalitySize","Value":10240},{"Name":"maxTotalRAMSize","Value":51200},{"Name":"maxServerGroups","Value":10},{"Name":"maxSecurityGroupRules","Value":20},{"Name":"maxTotalKeypairs","Value":100},{"Name":"totalCoresUsed","Value":4},{"Name":"totalRAMUsed","Value":8192},{"Name":"maxSecurityGroups","Value":10},{"Name":"totalFloatingIpsUsed","Value":0},{"Name":"totalInstancesUsed","Value":1},{"Name":"maxServerGroupMembers","Value":10},{"Name":"maxTotalFloatingIps","Value":10},{"Name":"totalSecurityGroupsUsed","Value":1},{"Name":"maxTotalCores","Value":20},{"Name":"totalSnapshotsUsed","Value":0},{"Name":"maxTotalBackups","Value":10},{"Name":"maxTotalVolumeGigabytes","Value":1000},{"Name":"maxTotalSnapshots","Value":10},{"Name":"maxTotalBackupGigabytes","Value":1000},{"Name":"totalBackupGigabytesUsed","Value":0},{"Name":"maxTotalVolumes","Value":10},{"Name":"totalVolumesUsed","Value":1},{"Name":"totalBackupsUsed","Value":0},{"Name":"totalGigabytesUsed","Value":2}]},
{"Demo":[{"Name":"maxServerMeta","Value":128},{"Name":"maxTotalInstances","Value":10},{"Name":"maxPersonality","Value":5},{"Name":"totalServerGroupsUsed","Value":0},{"Name":"maxImageMeta","Value":128},{"Name":"maxPersonalitySize","Value":10240},{"Name":"maxTotalRAMSize","Value":51200},{"Name":"maxServerGroups","Value":10},{"Name":"maxSecurityGroupRules","Value":20},{"Name":"maxTotalKeypairs","Value":100},{"Name":"totalCoresUsed","Value":2},{"Name":"totalRAMUsed","Value":4096},{"Name":"maxSecurityGroups","Value":10},{"Name":"totalFloatingIpsUsed","Value":0},{"Name":"totalInstancesUsed","Value":1},{"Name":"maxServerGroupMembers","Value":10},{"Name":"maxTotalFloatingIps","Value":10},{"Name":"totalSecurityGroupsUsed","Value":1},{"Name":"maxTotalCores","Value":20},{"Name":"totalSnapshotsUsed","Value":0},{"Name":"maxTotalBackups","Value":10},{"Name":"maxTotalVolumeGigabytes","Value":1000},{"Name":"maxTotalSnapshots","Value":10},{"Name":"maxTotalBackupGigabytes","Value":1000},{"Name":"totalBackupGigabytesUsed","Value":0},{"Name":"maxTotalVolumes","Value":10},{"Name":"totalVolumesUsed","Value":1},{"Name":"totalBackupsUsed","Value":0},{"Name":"totalGigabytesUsed","Value":2}]},
{"HYPERVISOR":[{"Field":"count","Value":6},{"Field":"current_workload","Value":0},{"Field":"disk_available_least","Value":45612},{"Field":"free_disk_gb","Value":48048},{"Field":"free_ram_mb","Value":2166564},{"Field":"local_gb","Value":49848},{"Field":"local_gb_used","Value":1800},{"Field":"memory_mb","Value":2320164},{"Field":"memory_mb_used","Value":153600},{"Field":"running_vms","Value":17},{"Field":"vcpus","Value":288},{"Field":"vcpus_used","Value":69}]}]}
